animact/__init__.py
animact/async_api.py
animact/base.py
animact/sync.py
animact-1.1.0.dist-info/licenses/LICENSE
animact-1.1.0.dist-info/METADATA
animact-1.1.0.dist-info/WHEEL
animact-1.1.0.dist-info/top_level.txt
animact-1.1.0.dist-info/RECORD
