Metadata-Version: 2.4
Name: animact
Version: 1.1.0
Summary: Anime-themed action and reaction image API wrapper for Python
Home-page: https://github.com/monabborhossain/animact
Author: Monabbor Hossain
Author-email: Monabbor Hossain <monabborhossain@gmail.com>
License: MIT License
Project-URL: Homepage, https://github.com/monabborhossain/animact
Project-URL: Documentation, https://github.com/monabborhossain/animact#readme
Project-URL: Repository, https://github.com/monabborhossain/animact.git
Project-URL: Issues, https://github.com/monabborhossain/animact/issues
Keywords: anime,reaction,image,api,async
Classifier: License :: OSI Approved :: MIT License
Classifier: Programming Language :: Python
Classifier: Programming Language :: Python :: 3
Classifier: Programming Language :: Python :: 3.7
Classifier: Programming Language :: Python :: 3.8
Classifier: Programming Language :: Python :: 3.9
Classifier: Programming Language :: Python :: 3.10
Classifier: Programming Language :: Python :: 3.11
Requires-Python: >=3.7
License-File: LICENSE
Requires-Dist: httpx>=0.24.0
Dynamic: author
Dynamic: home-page
Dynamic: license-file
Dynamic: requires-python
